{
    "type": "FeatureCollection",
    "features": [
        {
            "type": "Feature",
            "properties": {},
            "geometry": {
                "type": "LineString",
                "coordinates": [
                    [
                        4.399748,
                        45.44352
                    ],
                    [
                        4.463325,
                        45.440362
                    ],
                    [
                        4.464152,
                        45.440669
                    ],
                    [
                        4.576174,
                        45.512891
                    ],
                    [
                        4.577572,
                        45.513575
                    ],
                    [
                        4.7706,
                        45.59509
                    ],
                    [
                        4.772519,
                        45.596155
                    ],
                    [
                        4.790203,
                        45.591058
                    ],
                    [
                        4.790799,
                        45.591352
                    ],
                    [
                        4.851135,
                        45.661562
                    ],
                    [
                        4.853113,
                        45.666324
                    ],
                    [
                        4.859511,
                        45.76055
                    ]
                ]
            }
        }
    ]
}